BibliographicAPI/__init__.py
BibliographicAPI/api_usage.py
BibliographicAPI/crossref_api.py
BibliographicAPI/orcid_api.py
BibliographicAPI/publons_api.py
BibliographicAPI/scopus_api.py
kvv_BibliographicAPI-0.0.8.dist-info/LICENSE
kvv_BibliographicAPI-0.0.8.dist-info/METADATA
kvv_BibliographicAPI-0.0.8.dist-info/WHEEL
kvv_BibliographicAPI-0.0.8.dist-info/top_level.txt
kvv_BibliographicAPI-0.0.8.dist-info/RECORD
