Metadata-Version: 2.1
Name: kvv-BibliographicAPI
Version: 0.0.8
Summary: BibliographicAPI is used to access official APIs of several bibliographic databases
Home-page: https://github.com/VladKornilov/BibliographicAPI
Author: Vladislav Kornilov
Author-email: v.kornilovv@yandex.ru
Project-URL: Bug Tracker, https://github.com/VladKornilov/BibliographicAPI/issues
Classifier: Programming Language :: Python :: 3
Classifier: License :: OSI Approved :: Apache Software License
Classifier: Operating System :: OS Independent
Requires-Python: >=3.6
License-File: LICENSE
Requires-Dist: requests
Requires-Dist: crossrefapi
Requires-Dist: kvv-StoredObjects
